[
{
    "model": "account.emailaddress",
    "pk": 1,
    "fields": {
        "user": [
            "istvan.denes"
        ],
        "email": "istvan.denes@anthesisgroup.com",
        "verified": true,
        "primary": true
    }
},
{
    "model": "account.emailaddress",
    "pk": 2,
    "fields": {
        "user": [
            "ming.lee"
        ],
        "email": "ming.lee@anthesisgroup.com",
        "verified": true,
        "primary": true
    }
},
{
    "model": "account.emailaddress",
    "pk": 3,
    "fields": {
        "user": [
            "fionaplace"
        ],
        "email": "fiona.place@anthesisgroup.com",
        "verified": true,
        "primary": true
    }
},
{
    "model": "account.emailaddress",
    "pk": 4,
    "fields": {
        "user": [
            "michael.kelsall"
        ],
        "email": "michael.kelsall@anthesisgroup.com",
        "verified": true,
        "primary": true
    }
},
{
    "model": "account.emailaddress",
    "pk": 5,
    "fields": {
        "user": [
            "ali.stanton"
        ],
        "email": "Ali.Stanton@landmark.co.uk",
        "verified": true,
        "primary": true
    }
},
{
    "model": "account.emailaddress",
    "pk": 6,
    "fields": {
        "user": [
            "Tom.Venables"
        ],
        "email": "Tom.Venables@landmark.co.uk",
        "verified": true,
        "primary": true
    }
},
{
    "model": "account.emailaddress",
    "pk": 7,
    "fields": {
        "user": [
            "Constance.Blench"
        ],
        "email": "Constance.Blench@landmark.co.uk",
        "verified": true,
        "primary": true
    }
},
{
    "model": "account.emailaddress",
    "pk": 8,
    "fields": {
        "user": [
            "Simon.Boyle"
        ],
        "email": "Simon.Boyle@landmark.co.uk",
        "verified": true,
        "primary": true
    }
},
{
    "model": "account.emailaddress",
    "pk": 9,
    "fields": {
        "user": [
            "james.dobbin"
        ],
        "email": "james.dobbin@landmark.co.uk",
        "verified": true,
        "primary": true
    }
},
{
    "model": "account.emailaddress",
    "pk": 10,
    "fields": {
        "user": [
            "paul.messenger"
        ],
        "email": "paul.messenger@landmark.co.uk",
        "verified": true,
        "primary": true
    }
},
{
    "model": "account.emailaddress",
    "pk": 11,
    "fields": {
        "user": [
            "Jasmyn.Pierrepont"
        ],
        "email": "Jasmyn.Pierrepont@landmark.co.uk",
        "verified": true,
        "primary": true
    }
},
{
    "model": "account.emailaddress",
    "pk": 12,
    "fields": {
        "user": [
            "mandy.hawkins"
        ],
        "email": "mandy.hawkins@landmark.co.uk",
        "verified": true,
        "primary": true
    }
},
{
    "model": "account.emailaddress",
    "pk": 13,
    "fields": {
        "user": [
            "Ben.Shepherd"
        ],
        "email": "Ben.Shepherd@anthesisgroup.com",
        "verified": true,
        "primary": true
    }
},
{
    "model": "account.emailaddress",
    "pk": 14,
    "fields": {
        "user": [
            "tom.hall@landmark.co.uk"
        ],
        "email": "tom.hall@landmark.co.uk",
        "verified": true,
        "primary": true
    }
},
{
    "model": "account.emailaddress",
    "pk": 15,
    "fields": {
        "user": [
            "jake.hawkey"
        ],
        "email": "jake.hawkey@landmark.co.uk",
        "verified": true,
        "primary": true
    }
},
{
    "model": "account.emailaddress",
    "pk": 16,
    "fields": {
        "user": [
            "sally.redman@landmark.co.uk"
        ],
        "email": "sally.redman@landmark.co.uk",
        "verified": true,
        "primary": true
    }
},
{
    "model": "account.emailaddress",
    "pk": 17,
    "fields": {
        "user": [
            "Ben.Diallo@anthesisgroup.com"
        ],
        "email": "Ben.Diallo@anthesisgroup.com",
        "verified": true,
        "primary": true
    }
}
]
